setup.cfg
setup.py
bin/webdriver_controller
webdriver_controller/__init__.py
webdriver_controller/config.py
webdriver_controller/controller.py
webdriver_controller.egg-info/PKG-INFO
webdriver_controller.egg-info/SOURCES.txt
webdriver_controller.egg-info/dependency_links.txt
webdriver_controller.egg-info/requires.txt
webdriver_controller.egg-info/top_level.txt
webdriver_controller/drivers/__init__.py
webdriver_controller/drivers/chromedriver.py
webdriver_controller/drivers/geckodriver.py
webdriver_controller/drivers/selenium_standalone.py
webdriver_controller/utils/__init__.py
webdriver_controller/utils/async_client.py
webdriver_controller/utils/http_utils.py
webdriver_controller/utils/tools.py