Metadata-Version: 1.1
Name: webdriver-controller
Version: 0.0.4
Summary: a tool manages local Selenium Webdriver installation
Home-page: https://github.com/lcmtwn/webdriver_controller
Author: lcmtwn
Author-email: lcmtwn@gmail.com
License: MIT
Platform: UNKNOWN
Classifier: Programming Language :: Python :: 3
Classifier: Development Status :: 4 - Beta
Classifier: Environment :: Console
Classifier: Intended Audience :: Developers
Classifier: Operating System :: MacOS :: MacOS X
Classifier: License :: OSI Approved :: MIT License
Classifier: Topic :: Software Development :: Testing
